Metadata-Version: 1.1
Name: smycli
Version: 0.1.3
Summary: Base on  the MYCLI CLI for MySQL Database,add additional secure manner via ssh tunnel
Home-page: https://github.com/XGTIGER/smycli
Author: xgtiger
Author-email: xgtiger@163.com
License: MIT
Keywords: cli mysql mycli
Platform: UNKNOWN
Classifier: Intended Audience :: Developers
Classifier: License :: OSI Approved :: BSD License
Classifier: Operating System :: Unix
Classifier: Programming Language :: Python
Classifier: Programming Language :: Python :: 2.6
Classifier: Programming Language :: Python :: 2.7
Classifier: Programming Language :: Python :: 3
Classifier: Programming Language :: Python :: 3.3
Classifier: Programming Language :: Python :: 3.4
Classifier: Programming Language :: Python :: 3.5
Classifier: Programming Language :: SQL
Classifier: Topic :: Database
Classifier: Topic :: Database :: Front-Ends
Classifier: Topic :: Software Development
Classifier: Topic :: Software Development :: Libraries :: Python Modules
